wabclient/__init__.py
wabclient/client.py
wabclient/commands.py
wabclient/constants.py
wabclient/exceptions.py
wabclient/scripts/__init__.py
wabclient/scripts/cli.py
wabclient/tests/__init__.py
wabclient/tests/test_client.py
wabclient/tests/utils.py
wabclient-2.3.3.dist-info/LICENSE
wabclient-2.3.3.dist-info/METADATA
wabclient-2.3.3.dist-info/WHEEL
wabclient-2.3.3.dist-info/entry_points.txt
wabclient-2.3.3.dist-info/top_level.txt
wabclient-2.3.3.dist-info/RECORD
