Metadata-Version: 2.1
Name: wabclient
Version: 2.3.3
Summary: WhatsApp Business API Client
Home-page: https://github.com/praekeltfoundation/python-whatsapp-business-client
Author: Simon de Haan
Author-email: simon@praekelt.org
License: UNKNOWN
Keywords: whatsapp
Platform: UNKNOWN
Classifier: Intended Audience :: Developers
Classifier: Natural Language :: English
Classifier: Programming Language :: Python :: 3.6
Requires-Dist: requests
Requires-Dist: phonenumbers
Requires-Dist: iso8601
Requires-Dist: attrs
Provides-Extra: cli
Requires-Dist: limit ; extra == 'cli'
Requires-Dist: click ; extra == 'cli'
Provides-Extra: dev
Requires-Dist: pytest ; extra == 'dev'
Requires-Dist: responses ; extra == 'dev'
Requires-Dist: mock ; extra == 'dev'
